milea_users/__init__.py
milea_users/admin.py
milea_users/apps.py
milea_users/managers.py
milea_users/models.py
milea_users/settings.py
milea_users/tests.py
milea_users/locale/de/LC_MESSAGES/django.mo
milea_users/locale/de/LC_MESSAGES/django.po
milea_users/migrations/0001_initial.py
milea_users/migrations/__init__.py
milea_users/migrations/__pycache__/0001_initial.cpython-311.pyc
milea_users/migrations/__pycache__/0002_profile.cpython-311.pyc
milea_users/migrations/__pycache__/0002_remove_user_first_name_remove_user_last_name_profile.cpython-311.pyc
milea_users/migrations/__pycache__/0002_user_settings.cpython-311.pyc
milea_users/migrations/__pycache__/__init__.cpython-311.pyc
milea_users-0.2.1.dist-info/METADATA
milea_users-0.2.1.dist-info/WHEEL
milea_users-0.2.1.dist-info/top_level.txt
milea_users-0.2.1.dist-info/RECORD
