Metadata-Version: 2.1
Name: milea-users
Version: 0.2.1
Summary: Milea Framework - Milea Users Module
Author: red-pepper-services
Author-email: pypi@schiegg.at
License: MIT
Requires-Dist: milea-base >=0.1
